pycheckey/__init__.py
pycheckey/pycheckey.py
pycheckey-0.3.dist-info/METADATA
pycheckey-0.3.dist-info/RECORD
pycheckey-0.3.dist-info/WHEEL
pycheckey-0.3.dist-info/top_level.txt
