Metadata-Version: 2.1
Name: pycheckey
Version: 0.3
Summary: Ensure nested dictionary structure.
Home-page: https://github.com/dstarner/pycheckey
Author: Daniel Starner
Author-email: starner.daniel5@gmail.com
License: UNKNOWN
Platform: UNKNOWN
Classifier: Programming Language :: Python :: 3
Classifier: License :: OSI Approved :: MIT License
Classifier: Operating System :: OS Independent
Requires-Python: >3.5.2
